{".class":"MypyFile","_fullname":"services.service_service","future_import_flags":[],"is_partial_stub_package":false,"is_stub":false,"names":{".class":"SymbolTable","EventBus":{".class":"SymbolTableNode","cross_ref":"core.event_bus.EventBus","kind":"Gdef"},"Repository":{".class":"SymbolTableNode","cross_ref":"core.repository.Repository","kind":"Gdef"},"ServiceService":{".class":"SymbolTableNode","kind":"Gdef","node":{".class":"TypeInfo","_promote":[],"abstract_attributes":[],"alt_promote":null,"bases":["builtins.object"],"dataclass_transform_spec":null,"declared_metaclass":null,"defn":{".class":"ClassDef","fullname":"services.service_service.ServiceService","name":"ServiceService","type_vars":[]},"deletable_attributes":[],"deprecated":null,"flags":[],"fullname":"services.service_service.ServiceService","has_param_spec_type":false,"metaclass_type":null,"metadata":{},"module_name":"services.service_service","mro":["services.service_service.ServiceService","builtins.object"],"names":{".class":"SymbolTable","__init__":{".class":"SymbolTableNode","kind":"Mdef","node":{".class":"FuncDef","abstract_status":0,"arg_kinds":[0,0,0,0],"arg_names":["self","repository","event_bus","settings_service"],"dataclass_transform_spec":null,"deprecated":null,"flags":["is_trivial_self"],"fullname":"services.service_service.ServiceService.__init__","name":"__init__","original_first_arg":"self","type":{".class":"CallableType","arg_kinds":[0,0,0,0],"arg_names":["self","repository","event_bus","settings_service"],"arg_types":["services.service_service.ServiceService","core.repository.Repository","core.event_bus.EventBus","services.settings_service.SettingsService"],"fallback":"builtins.function","from_concatenate":false,"implicit":false,"imprecise_arg_kinds":false,"is_bound":false,"is_ellipsis_args":false,"name":"__init__ of ServiceService","ret_type":{".class":"NoneType"},"type_guard":null,"type_is":null,"unpack_kwargs":false,"variables":[]}}},"bus":{".class":"SymbolTableNode","implicit":true,"kind":"Mdef","node":{".class":"Var","flags":["is_ready","is_inferred"],"fullname":"services.service_service.ServiceService.bus","name":"bus","setter_type":null,"type":"core.event_bus.EventBus"}},"create_service":{".class":"SymbolTableNode","kind":"Mdef","node":{".class":"FuncDef","abstract_status":0,"arg_kinds":[0,0],"arg_names":["self","service_data"],"dataclass_transform_spec":null,"deprecated":null,"flags":["is_trivial_self"],"fullname":"services.service_service.ServiceService.create_service","name":"create_service","original_first_arg":"self","type":{".class":"CallableType","arg_kinds":[0,0],"arg_names":["self","service_data"],"arg_types":["services.service_service.ServiceService",{".class":"Instance","args":[{".class":"AnyType","missing_import_name":null,"source_any":null,"type_of_any":4},{".class":"AnyType","missing_import_name":null,"source_any":null,"type_of_any":4}],"extra_attrs":null,"type_ref":"builtins.dict"}],"fallback":"builtins.function","from_concatenate":false,"implicit":false,"imprecise_arg_kinds":false,"is_bound":false,"is_ellipsis_args":false,"name":"create_service of ServiceService","ret_type":"core.schemas.Service","type_guard":null,"type_is":null,"unpack_kwargs":false,"variables":[]}}},"delete_service":{".class":"SymbolTableNode","kind":"Mdef","node":{".class":"FuncDef","abstract_status":0,"arg_kinds":[0,0],"arg_names":["self","service_id"],"dataclass_transform_spec":null,"deprecated":null,"flags":["is_trivial_self"],"fullname":"services.service_service.ServiceService.delete_service","name":"delete_service","original_first_arg":"self","type":{".class":"CallableType","arg_kinds":[0,0],"arg_names":["self","service_id"],"arg_types":["services.service_service.ServiceService","builtins.str"],"fallback":"builtins.function","from_concatenate":false,"implicit":false,"imprecise_arg_kinds":false,"is_bound":false,"is_ellipsis_args":false,"name":"delete_service of ServiceService","ret_type":"builtins.bool","type_guard":null,"type_is":null,"unpack_kwargs":false,"variables":[]}}},"get_all_services":{".class":"SymbolTableNode","kind":"Mdef","node":{".class":"FuncDef","abstract_status":0,"arg_kinds":[0],"arg_names":["self"],"dataclass_transform_spec":null,"deprecated":null,"flags":["is_trivial_self"],"fullname":"services.service_service.ServiceService.get_all_services","name":"get_all_services","original_first_arg":"self","type":{".class":"CallableType","arg_kinds":[0],"arg_names":["self"],"arg_types":["services.service_service.ServiceService"],"fallback":"builtins.function","from_concatenate":false,"implicit":false,"imprecise_arg_kinds":false,"is_bound":false,"is_ellipsis_args":false,"name":"get_all_services of ServiceService","ret_type":{".class":"Instance","args":["core.schemas.Service"],"extra_attrs":null,"type_ref":"builtins.list"},"type_guard":null,"type_is":null,"unpack_kwargs":false,"variables":[]}}},"get_archived_services":{".class":"SymbolTableNode","kind":"Mdef","node":{".class":"FuncDef","abstract_status":0,"arg_kinds":[0],"arg_names":["self"],"dataclass_transform_spec":null,"deprecated":null,"flags":["is_trivial_self"],"fullname":"services.service_service.ServiceService.get_archived_services","name":"get_archived_services","original_first_arg":"self","type":{".class":"CallableType","arg_kinds":[0],"arg_names":["self"],"arg_types":["services.service_service.ServiceService"],"fallback":"builtins.function","from_concatenate":false,"implicit":false,"imprecise_arg_kinds":false,"is_bound":false,"is_ellipsis_args":false,"name":"get_archived_services of ServiceService","ret_type":{".class":"Instance","args":["core.schemas.Service"],"extra_attrs":null,"type_ref":"builtins.list"},"type_guard":null,"type_is":null,"unpack_kwargs":false,"variables":[]}}},"repo":{".class":"SymbolTableNode","implicit":true,"kind":"Mdef","node":{".class":"Var","flags":["is_ready","is_inferred"],"fullname":"services.service_service.ServiceService.repo","name":"repo","setter_type":null,"type":"core.repository.Repository"}},"settings_service":{".class":"SymbolTableNode","implicit":true,"kind":"Mdef","node":{".class":"Var","flags":["is_ready","is_inferred"],"fullname":"services.service_service.ServiceService.settings_service","name":"settings_service","setter_type":null,"type":"services.settings_service.SettingsService"}},"update_service":{".class":"SymbolTableNode","kind":"Mdef","node":{".class":"FuncDef","abstract_status":0,"arg_kinds":[0,0,0],"arg_names":["self","service_id","new_data"],"dataclass_transform_spec":null,"deprecated":null,"flags":["is_trivial_self"],"fullname":"services.service_service.ServiceService.update_service","name":"update_service","original_first_arg":"self","type":{".class":"CallableType","arg_kinds":[0,0,0],"arg_names":["self","service_id","new_data"],"arg_types":["services.service_service.ServiceService","builtins.str",{".class":"Instance","args":[{".class":"AnyType","missing_import_name":null,"source_any":null,"type_of_any":4},{".class":"AnyType","missing_import_name":null,"source_any":null,"type_of_any":4}],"extra_attrs":null,"type_ref":"builtins.dict"}],"fallback":"builtins.function","from_concatenate":false,"implicit":false,"imprecise_arg_kinds":false,"is_bound":false,"is_ellipsis_args":false,"name":"update_service of ServiceService","ret_type":{".class":"UnionType","items":["core.schemas.Service",{".class":"NoneType"}],"uses_pep604_syntax":true},"type_guard":null,"type_is":null,"unpack_kwargs":false,"variables":[]}}}},"self_type":{".class":"TypeVarType","default":{".class":"AnyType","missing_import_name":null,"source_any":null,"type_of_any":4},"fullname":"services.service_service.ServiceService.Self","id":0,"name":"Self","namespace":"","upper_bound":"services.service_service.ServiceService","values":[],"variance":0},"slots":null,"tuple_type":null,"type_vars":[],"typeddict_type":null}},"SettingsService":{".class":"SymbolTableNode","cross_ref":"services.settings_service.SettingsService","kind":"Gdef"},"__annotations__":{".class":"SymbolTableNode","kind":"Gdef","node":{".class":"Var","flags":["is_ready"],"fullname":"services.service_service.__annotations__","name":"__annotations__","setter_type":null,"type":{".class":"Instance","args":["builtins.str",{".class":"AnyType","missing_import_name":null,"source_any":null,"type_of_any":6}],"extra_attrs":null,"type_ref":"builtins.dict"}}},"__doc__":{".class":"SymbolTableNode","kind":"Gdef","node":{".class":"Var","flags":["is_ready"],"fullname":"services.service_service.__doc__","name":"__doc__","setter_type":null,"type":"builtins.str"}},"__file__":{".class":"SymbolTableNode","kind":"Gdef","node":{".class":"Var","flags":["is_ready"],"fullname":"services.service_service.__file__","name":"__file__","setter_type":null,"type":"builtins.str"}},"__name__":{".class":"SymbolTableNode","kind":"Gdef","node":{".class":"Var","flags":["is_ready"],"fullname":"services.service_service.__name__","name":"__name__","setter_type":null,"type":"builtins.str"}},"__package__":{".class":"SymbolTableNode","kind":"Gdef","node":{".class":"Var","flags":["is_ready"],"fullname":"services.service_service.__package__","name":"__package__","setter_type":null,"type":"builtins.str"}},"__spec__":{".class":"SymbolTableNode","kind":"Gdef","node":{".class":"Var","flags":["is_ready"],"fullname":"services.service_service.__spec__","name":"__spec__","setter_type":null,"type":"_frozen_importlib.ModuleSpec"}},"app_signals":{".class":"SymbolTableNode","cross_ref":"core.signals.app_signals","kind":"Gdef"},"get_cache":{".class":"SymbolTableNode","cross_ref":"core.cache_manager.get_cache","kind":"Gdef"},"get_logger":{".class":"SymbolTableNode","cross_ref":"core.logger.get_logger","kind":"Gdef"},"invalidate_cache":{".class":"SymbolTableNode","cross_ref":"core.cache_manager.invalidate_cache","kind":"Gdef"},"logger":{".class":"SymbolTableNode","kind":"Gdef","node":{".class":"Var","flags":["is_ready","is_inferred","has_explicit_value"],"fullname":"services.service_service.logger","name":"logger","setter_type":null,"type":"logging.Logger"}},"notify_operation":{".class":"SymbolTableNode","cross_ref":"core.notification_bridge.notify_operation","kind":"Gdef"},"schemas":{".class":"SymbolTableNode","cross_ref":"core.schemas","kind":"Gdef"}},"path":".\\services\\service_service.py"}